CHANGES.txt
LICENSE.txt
MANIFEST.in
README.md
requirements.txt
setup.py
paegan/__init__.py
paegan/location4d.py
paegan.egg-info/PKG-INFO
paegan.egg-info/SOURCES.txt
paegan.egg-info/dependency_links.txt
paegan.egg-info/namespace_packages.txt
paegan.egg-info/requires.txt
paegan.egg-info/top_level.txt
paegan/cdm/__init__.py
paegan/cdm/dataset.py
paegan/cdm/depthvar.py
paegan/cdm/gridvar.py
paegan/cdm/timevar.py
paegan/cdm/variable.py
paegan/cdm/writer.py
paegan/cdm/dsg/__init__.py
paegan/cdm/dsg/member.py
paegan/cdm/dsg/collections/__init__.py
paegan/cdm/dsg/collections/station_collection.py
paegan/cdm/dsg/collections/base/__init__.py
paegan/cdm/dsg/collections/base/feature_collection.py
paegan/cdm/dsg/collections/base/nested_point_collection.py
paegan/cdm/dsg/collections/base/point_collection.py
paegan/cdm/dsg/collections/base/profile_collection.py
paegan/cdm/dsg/collections/base/section_collection.py
paegan/cdm/dsg/collections/base/trajectory_collection.py
paegan/cdm/dsg/features/__init__.py
paegan/cdm/dsg/features/station.py
paegan/cdm/dsg/features/station_profile.py
paegan/cdm/dsg/features/base/__init__.py
paegan/cdm/dsg/features/base/feature.py
paegan/cdm/dsg/features/base/point.py
paegan/cdm/dsg/features/base/profile.py
paegan/cdm/dsg/features/base/section.py
paegan/cdm/dsg/features/base/trajectory.py
paegan/cdm/grids/__init__.py
paegan/cdm/grids/c_grid.py
paegan/cdm/grids/n_cell.py
paegan/cdm/grids/r_grid.py
paegan/cdm/grids/u_grid.py
paegan/external/__init__.py
paegan/external/greatcircle.py
paegan/logger/__init__.py
paegan/logger/easy_logger.py
paegan/logger/multi_process_logging.py
paegan/logger/null_handler.py
paegan/logger/progress_handler.py
paegan/logger/redis_handler.py
paegan/roms/__init__.py
paegan/roms/roms.py
paegan/utils/__init__.py
paegan/utils/asagreatcircle.py
paegan/utils/asainterpolate.py
paegan/utils/asalist.py
paegan/utils/asamath.py
paegan/utils/asarandom.py
paegan/utils/asaregrid.py
paegan/utils/datetime.py